charq/__init_.py
charq/__main__.py
charq/charq.py
charq-0.0.3.dist-info/LICENSE
charq-0.0.3.dist-info/METADATA
charq-0.0.3.dist-info/WHEEL
charq-0.0.3.dist-info/top_level.txt
charq-0.0.3.dist-info/RECORD
