Metadata-Version: 2.1
Name: charq
Version: 0.0.3
Summary: A simple package that provides methods to get characters, numbers, random words and etc.
Home-page: https://github.com/joaoroberto50/CharQ
Author: João Roberto
Author-email: joaorobert0@protonmail.com
License: MIT
Project-URL: Bug Tracker, https://github.com/joaoroberto50/CharQ/issues
Platform: UNKNOWN
Classifier: Programming Language :: Python :: 3
Classifier: License :: OSI Approved :: MIT License
Classifier: Operating System :: OS Independent
Requires-Python: >=3.6
